convertempPy/__init__.py
convertempPy/convertempPy.py
convertemppy-4.0.0.dist-info/LICENSE
convertemppy-4.0.0.dist-info/WHEEL
convertemppy-4.0.0.dist-info/METADATA
convertemppy-4.0.0.dist-info/RECORD
