Metadata-Version: 2.1
Name: convertemppy
Version: 4.0.0
Summary: Easily convert between temperatures!
Home-page: https://github.com/ttimbers/convertempPy
License: MIT
Keywords: temperature,conversion
Author: ttimbers
Author-email: tiffany.timbers@stat.ubc.ca
Requires-Python: >=3.7,<4.0
Classifier: License :: OSI Approved :: MIT License
Classifier: Programming Language :: Python :: 3
Classifier: Programming Language :: Python :: 3.7
Classifier: Programming Language :: Python :: 3.8
Project-URL: Documentation, https://convertempPy.readthedocs.io
Project-URL: Repository, https://github.com/ttimbers/convertempPy
